{"kind":"identitytoolkit#DownloadAccountResponse","users":[{"localId":"OEOPuejWxnFfHX19P85QkQg7PeRe","createdAt":"1667930189458","lastLoginAt":"1667930189458","displayName":"PingHe","photoUrl":"","passwordHash":"fakeHash:salt=fakeSaltPSR7Qz4IvTONrleRdMVM:password=Hepingx1997","salt":"fakeSaltPSR7Qz4IvTONrleRdMVM","passwordUpdatedAt":1667945354538,"providerUserInfo":[{"providerId":"password","email":"hxxp0204@gmail.com","federatedId":"hxxp0204@gmail.com","rawId":"hxxp0204@gmail.com","displayName":"PingHe","photoUrl":""}],"validSince":"1667945354","email":"hxxp0204@gmail.com","emailVerified":true,"disabled":false}]}